{"nodes":[{"id":"backend_test_audio_playback_py","label":"test_audio_playback","source_file":".\\backend\\test_audio_playback.py","node_type":"file"},{"id":"backend_test_audio_playback_py_import_requests","label":"requests","source_file":".\\backend\\test_audio_playback.py","source_location":"L5","node_type":"module"},{"id":"backend_test_audio_playback_py_import_json","label":"json","source_file":".\\backend\\test_audio_playback.py","source_location":"L6","node_type":"module"},{"id":"backend_test_audio_playback_py_import_os","label":"os","source_file":".\\backend\\test_audio_playback.py","source_location":"L7","node_type":"module"},{"id":"backend_test_audio_playback_py_test_sessions_endpoint","label":"test_sessions_endpoint()","source_file":".\\backend\\test_audio_playback.py","source_location":"L12","node_type":"function"},{"id":"backend_test_audio_playback_py_test_audio_file_access","label":"test_audio_file_access()","source_file":".\\backend\\test_audio_playback.py","source_location":"L48","node_type":"function"},{"id":"backend_test_audio_playback_py_test_direct_audio_access","label":"test_direct_audio_access()","source_file":".\\backend\\test_audio_playback.py","source_location":"L113","node_type":"function"},{"id":"backend_test_audio_playback_py_test_media_directory_listing","label":"test_media_directory_listing()","source_file":".\\backend\\test_audio_playback.py","source_location":"L150","node_type":"function"},{"id":"backend_test_audio_playback_py_main","label":"main()","source_file":".\\backend\\test_audio_playback.py","source_location":"L186","node_type":"function"}],"edges":[{"source":"backend_test_audio_playback_py","target":"backend_test_audio_playback_py_import_requests","relation":"imports","confidence":"EXTRACTED","confidence_score":1.0,"source_file":".\\backend\\test_audio_playback.py","source_location":"L5","weight":1.0},{"source":"backend_test_audio_playback_py","target":"backend_test_audio_playback_py_import_json","relation":"imports","confidence":"EXTRACTED","confidence_score":1.0,"source_file":".\\backend\\test_audio_playback.py","source_location":"L6","weight":1.0},{"source":"backend_test_audio_playback_py","target":"backend_test_audio_playback_py_import_os","relation":"imports","confidence":"EXTRACTED","confidence_score":1.0,"source_file":".\\backend\\test_audio_playback.py","source_location":"L7","weight":1.0},{"source":"backend_test_audio_playback_py","target":"backend_test_audio_playback_py_test_sessions_endpoint","relation":"defines","confidence":"EXTRACTED","confidence_score":1.0,"source_file":".\\backend\\test_audio_playback.py","source_location":"L12","weight":1.0},{"source":"backend_test_audio_playback_py","target":"backend_test_audio_playback_py_test_audio_file_access","relation":"defines","confidence":"EXTRACTED","confidence_score":1.0,"source_file":".\\backend\\test_audio_playback.py","source_location":"L48","weight":1.0},{"source":"backend_test_audio_playback_py","target":"backend_test_audio_playback_py_test_direct_audio_access","relation":"defines","confidence":"EXTRACTED","confidence_score":1.0,"source_file":".\\backend\\test_audio_playback.py","source_location":"L113","weight":1.0},{"source":"backend_test_audio_playback_py","target":"backend_test_audio_playback_py_test_media_directory_listing","relation":"defines","confidence":"EXTRACTED","confidence_score":1.0,"source_file":".\\backend\\test_audio_playback.py","source_location":"L150","weight":1.0},{"source":"backend_test_audio_playback_py","target":"backend_test_audio_playback_py_main","relation":"defines","confidence":"EXTRACTED","confidence_score":1.0,"source_file":".\\backend\\test_audio_playback.py","source_location":"L186","weight":1.0},{"source":"backend_test_audio_playback_py_main","target":"backend_test_audio_playback_py_test_sessions_endpoint","relation":"calls","confidence":"INFERRED","confidence_score":0.7,"source_file":".\\backend\\test_audio_playback.py","weight":1.0},{"source":"backend_test_audio_playback_py_main","target":"backend_test_audio_playback_py_test_audio_file_access","relation":"calls","confidence":"INFERRED","confidence_score":0.7,"source_file":".\\backend\\test_audio_playback.py","weight":1.0},{"source":"backend_test_audio_playback_py_main","target":"backend_test_audio_playback_py_test_direct_audio_access","relation":"calls","confidence":"INFERRED","confidence_score":0.7,"source_file":".\\backend\\test_audio_playback.py","weight":1.0},{"source":"backend_test_audio_playback_py_main","target":"backend_test_audio_playback_py_test_media_directory_listing","relation":"calls","confidence":"INFERRED","confidence_score":0.7,"source_file":".\\backend\\test_audio_playback.py","weight":1.0}],"hyperedges":[]}